gibbscorrections/__init__.py
gibbscorrections/corrections.py
gibbscorrections/molecule.py
gibbscorrections/orca_job.py
gibbscorrections-0.4.0.dist-info/METADATA
gibbscorrections-0.4.0.dist-info/WHEEL
gibbscorrections-0.4.0.dist-info/entry_points.txt
gibbscorrections-0.4.0.dist-info/top_level.txt
gibbscorrections-0.4.0.dist-info/RECORD
