Metadata-Version: 2.1
Name: gibbscorrections
Version: 0.4.0
Summary: UNKNOWN
Home-page: http://github.com/chemistry-scripts/gibbscorrections
Author: Emmanuel Nicolas
Author-email: latruelle@users.noreply.github.com
License: MIT
Platform: UNKNOWN
